Metadata-Version: 1.0
Name: SentiVizu-txt
Version: 0.0.1
Summary: A sentiment analysis on text of different languages. Data visualization on sentiment analysis
Home-page: UNKNOWN
Author: JINKA THE AVIRAJ
Author-email: jinkatheaviraj@gmail.com
License: UNKNOWN
Platform: UNKNOWN
